get_all_files/__init__.py
get_all_files/_get_all_files.py
get_all_files-0.3.0.dist-info/LICENSE
get_all_files-0.3.0.dist-info/METADATA
get_all_files-0.3.0.dist-info/WHEEL
get_all_files-0.3.0.dist-info/RECORD
