Metadata-Version: 2.1
Name: get-all-files
Version: 0.3.0
Summary: a simple package to get all files with given file extension in a directory
License: LICENSE
Author: brendan whelan
Author-email: bwheelz360@gmail.com
Requires-Python: >=3.8.1,<4.0.0
Classifier: License :: Other/Proprietary License
Classifier: Programming Language :: Python :: 3
Classifier: Programming Language :: Python :: 3.9
Classifier: Programming Language :: Python :: 3.10
Classifier: Programming Language :: Python :: 3.11
